xlsxpandasformatter/__init__.py
xlsxpandasformatter/_version.py
xlsxpandasformatter/xlsxpandasformatter.py
xlsxpandasformatter/xlsxpandasformatter_example.py
XlsxPandasFormatter-0.0.2.dist-info/LICENSE
XlsxPandasFormatter-0.0.2.dist-info/METADATA
XlsxPandasFormatter-0.0.2.dist-info/WHEEL
XlsxPandasFormatter-0.0.2.dist-info/top_level.txt
XlsxPandasFormatter-0.0.2.dist-info/RECORD
