Metadata-Version: 2.1
Name: XlsxPandasFormatter
Version: 0.0.2
Summary: XlsxPandasFormatter
Home-page: https://github.com/webermarcolivier/xlsxpandasformatter
Author: Marc Weber
Author-email: 329640305@qq.com
License: MIT
Project-URL: Repository, https://github.com/webermarcolivier/xlsxpandasformatter
Project-URL: Bug Reports, https://github.com/webermarcolivier/xlsxpandasformatter/issues
Project-URL: Documentation, https://github.com/webermarcolivier/xlsxpandasformatter/blob/master/README.md
Keywords: xlsxpandasformatter xlsx excel pandas formatter
Platform: UNKNOWN
Classifier: Development Status :: 5 - Production/Stable
Classifier: Intended Audience :: Developers
Classifier: License :: OSI Approved :: MIT License
Classifier: Topic :: Software Development :: Libraries :: Python Modules
Classifier: Programming Language :: Python :: 3
Classifier: Programming Language :: Python :: 3 :: Only
Classifier: Programming Language :: Python :: 3.6
Classifier: Programming Language :: Python :: 3.7
Classifier: Programming Language :: Python :: 3.8
Classifier: Programming Language :: Python :: 3.9
Requires-Python: >=3.6
Requires-Dist: pandas
Requires-Dist: XlsxWriter
Requires-Dist: matplotlib
Requires-Dist: numpy
Requires-Dist: seaborn
